permissionedforms/__init__.py
permissionedforms/forms.py
django_permissionedforms-0.1.dist-info/LICENSE
django_permissionedforms-0.1.dist-info/METADATA
django_permissionedforms-0.1.dist-info/WHEEL
django_permissionedforms-0.1.dist-info/top_level.txt
django_permissionedforms-0.1.dist-info/RECORD
