Metadata-Version: 2.1
Name: django-permissionedforms
Version: 0.1
Summary: Django extension for creating forms that vary according to user permissions
Home-page: https://github.com/wagtail/django-permissionedforms
Author: Matthew Westcott
Author-email: matthew.westcott@torchbox.com
License: BSD
Platform: UNKNOWN
Classifier: Development Status :: 4 - Beta
Classifier: Environment :: Web Environment
Classifier: Intended Audience :: Developers
Classifier: License :: OSI Approved :: BSD License
Classifier: Operating System :: OS Independent
Classifier: Programming Language :: Python
Classifier: Programming Language :: Python :: 3
Classifier: Programming Language :: Python :: 3.7
Classifier: Programming Language :: Python :: 3.8
Classifier: Programming Language :: Python :: 3.9
Classifier: Programming Language :: Python :: 3.10
Classifier: Programming Language :: Python :: 3 :: Only
Classifier: Framework :: Django
Requires-Python: >=3.7
Provides-Extra: testing
